teamlistdevops.py
teamlistdevops-1.0.3.dist-info/METADATA
teamlistdevops-1.0.3.dist-info/WHEEL
teamlistdevops-1.0.3.dist-info/top_level.txt
teamlistdevops-1.0.3.dist-info/RECORD
