Metadata-Version: 2.1
Name: teamlistdevops
Version: 1.0.3
Summary: Displays the DevOps Team List of Presidio
Author: Ananth S S
Author-email: ananthsekar007@gmail.com
Classifier: Programming Language :: Python :: 3
Classifier: License :: OSI Approved :: MIT License
Classifier: Operating System :: OS Independent
Requires-Python: >=3.6
Requires-Dist: ascii-magic ==2.3.0
Requires-Dist: colorama ==0.4.6
Requires-Dist: requests ==2.31.0
